watson_jira_next/__init__.py
watson_jira_next/cli.py
watson_jira_next/src/__init__.py
watson_jira_next/src/config.py
watson_jira_next/src/jira.py
watson_jira_next/src/mapper.py
watson_jira_next/src/watson.py
watson_jira_next/tests/test_cli.py
watson_jira_next-0.3.3.dist-info/entry_points.txt
watson_jira_next-0.3.3.dist-info/LICENSE
watson_jira_next-0.3.3.dist-info/WHEEL
watson_jira_next-0.3.3.dist-info/METADATA
watson_jira_next-0.3.3.dist-info/RECORD
