Metadata-Version: 2.1
Name: watson-jira-next
Version: 0.3.3
Summary: Format and upload Watson time logs to Jira as Tempo worklogs
License: MIT License (MIT)
Author: matus.benko
Author-email: matus.benko@gmail.com
Requires-Python: >=3.9,<4.0
Classifier: Development Status :: 3 - Alpha
Classifier: License :: OSI Approved :: MIT License
Classifier: License :: Other/Proprietary License
Classifier: Programming Language :: Python :: 3
Classifier: Programming Language :: Python :: 3.10
Classifier: Programming Language :: Python :: 3.6
Classifier: Programming Language :: Python :: 3.9
Classifier: Topic :: Office/Business :: Scheduling
Requires-Dist: PyYAML (>=6.0,<7.0)
Requires-Dist: click (>=8.1.3,<9.0.0)
Requires-Dist: colorama (>=0.4.4,<0.5.0)
Requires-Dist: jira (>=3.2.0,<4.0.0)
Requires-Dist: python-dateutil (>=2.8.2,<3.0.0)
Requires-Dist: pyxdg (>=0.28,<0.29)
Requires-Dist: simplejson (>=3.17.6,<4.0.0)
Requires-Dist: td-watson (>=2.1.0,<3.0.0)
